{
  "TESTER:RUN-1773895697078-838": {
    "status": null,
    "closeReason": null,
    "updatedAt": "2026-03-19T05:31:34.111274+00:00",
    "triggeredAt": null,
    "closedAt": null
  },
  "EBass:RUN-1773830537523-76": {
    "status": "sl-hit",
    "closeReason": "SL",
    "updatedAt": "2026-03-19T06:35:33.277185+00:00",
    "triggeredAt": 1773830700,
    "closedAt": 1773830700
  },
  "EKlaETun:RUN-1773883928181-290": {
    "status": "pending",
    "closeReason": null,
    "updatedAt": "2026-03-19T06:35:33.277185+00:00",
    "triggeredAt": null,
    "closedAt": null
  },
  "TESTER:RUN-1773899597434-486": {
    "status": null,
    "closeReason": null,
    "updatedAt": "2026-03-19T06:35:33.277185+00:00",
    "triggeredAt": null,
    "closedAt": null
  },
  "TESTER:RUN-1773903198203-456": {
    "status": null,
    "closeReason": null,
    "updatedAt": "2026-03-19T07:51:50.693398+00:00",
    "triggeredAt": null,
    "closedAt": null
  },
  "EBass:RUN-1773905838669-337": {
    "status": null,
    "closeReason": null,
    "updatedAt": "2026-03-19T07:51:50.693398+00:00",
    "triggeredAt": null,
    "closedAt": null
  },
  "EKlaETun:RUN-1773906126810-675": {
    "status": null,
    "closeReason": null,
    "updatedAt": "2026-03-19T07:51:50.693398+00:00",
    "triggeredAt": null,
    "closedAt": null
  },
  "TESTER:RUN-1773906798801-353": {
    "status": "pending",
    "closeReason": null,
    "updatedAt": "2026-03-19T16:00:41.802912+00:00",
    "triggeredAt": null,
    "closedAt": null
  },
  "EBass:RUN-1773909443022-799": {
    "status": null,
    "closeReason": null,
    "updatedAt": "2026-03-19T08:53:39.687789+00:00",
    "triggeredAt": null,
    "closedAt": null
  },
  "EKlaETun:RUN-1773909728631-131": {
    "status": null,
    "closeReason": null,
    "updatedAt": "2026-03-19T08:53:39.687789+00:00",
    "triggeredAt": null,
    "closedAt": null
  },
  "EBass:RUN-1773913045062-242": {
    "status": null,
    "closeReason": null,
    "updatedAt": "2026-03-19T09:54:35.333905+00:00",
    "triggeredAt": null,
    "closedAt": null
  },
  "EKlaETun:RUN-1773913331063-883": {
    "status": null,
    "closeReason": null,
    "updatedAt": "2026-03-19T09:54:35.333905+00:00",
    "triggeredAt": null,
    "closedAt": null
  },
  "EBass:RUN-1773916939840-366": {
    "status": null,
    "closeReason": null,
    "updatedAt": "2026-03-19T11:41:30.422347+00:00",
    "triggeredAt": null,
    "closedAt": null
  },
  "EKlaETun:RUN-1773917236983-366": {
    "status": null,
    "closeReason": null,
    "updatedAt": "2026-03-19T11:41:30.422347+00:00",
    "triggeredAt": null,
    "closedAt": null
  },
  "EBass:RUN-1773924146872-598": {
    "status": null,
    "closeReason": null,
    "updatedAt": "2026-03-19T13:21:49.822531+00:00",
    "triggeredAt": null,
    "closedAt": null
  },
  "EKlaETun:RUN-1773924733672-709": {
    "status": null,
    "closeReason": null,
    "updatedAt": "2026-03-19T13:21:49.822531+00:00",
    "triggeredAt": null,
    "closedAt": null
  },
  "EBass:RUN-1773928040486-502": {
    "status": null,
    "closeReason": null,
    "updatedAt": "2026-03-19T14:30:19.943261+00:00",
    "triggeredAt": null,
    "closedAt": null
  },
  "EKlaETun:RUN-1773928336763-869": {
    "status": null,
    "closeReason": null,
    "updatedAt": "2026-03-19T14:30:19.943261+00:00",
    "triggeredAt": null,
    "closedAt": null
  },
  "EBass:RUN-1773931647353-326": {
    "status": null,
    "closeReason": null,
    "updatedAt": "2026-03-19T16:00:41.802912+00:00",
    "triggeredAt": null,
    "closedAt": null
  },
  "EKlaETun:RUN-1773932232616-69": {
    "status": null,
    "closeReason": null,
    "updatedAt": "2026-03-19T16:00:41.802912+00:00",
    "triggeredAt": null,
    "closedAt": null
  }
}