{
  "generatedAt": "2026-04-13T14:15:09.350633+00:00",
  "symbol": "XAUUSD",
  "interval": "15min",
  "qualityGate": {
    "ok": true,
    "issues": []
  },
  "candles": {
    "count": 1000,
    "from": 1774530900,
    "to": 1776074400
  },
  "summary": {
    "totalOrders": 3,
    "triggeredOrders": 1,
    "slHits": 0,
    "tp1Hits": 0,
    "tpMostHits": 1,
    "winRate": 100.0
  },
  "orders": [
    {
      "source": "TESTER",
      "runId": "RUN-1775058643394-951",
      "orderKey": "TESTER:RUN-1775058643394-951",
      "createdAt": "2026-04-01T15:51:49.489Z",
      "orderType": "BUY_LIMIT",
      "entry": 4755.0,
      "sl": 4734.9,
      "tp1": 4784.39,
      "tpMost": 4784.39,
      "result": {
        "status": "tpmost-hit",
        "triggered": true,
        "triggeredAt": 1775061000,
        "closeReason": "TPMost",
        "closedAt": 1775070000,
        "timeInTradeMin": 150,
        "mfe": 36.8,
        "mae": -3.02
      }
    },
    {
      "source": "EBass",
      "runId": "RUN-1776088036075-751",
      "orderKey": "EBass:RUN-1776088036075-751",
      "createdAt": "2026-04-13T13:49:17.731Z",
      "orderType": "SELL_LIMIT",
      "entry": 4735.05,
      "sl": 4736.85,
      "tp1": 4730.74,
      "tpMost": 4724.94,
      "result": {
        "status": null,
        "triggered": false,
        "triggeredAt": null,
        "closeReason": null,
        "closedAt": null,
        "timeInTradeMin": null,
        "mfe": 0.0,
        "mae": 0.0
      }
    },
    {
      "source": "EKlaETun",
      "runId": "RUN-1776082782985-0",
      "orderKey": "EKlaETun:RUN-1776082782985-0",
      "createdAt": "2026-04-13T12:25:16.298Z",
      "orderType": "BUY_LIMIT",
      "entry": 4706.5,
      "sl": 4703.5,
      "tp1": 4716.0,
      "tpMost": 4720.11,
      "result": {
        "status": null,
        "triggered": false,
        "triggeredAt": null,
        "closeReason": null,
        "closedAt": null,
        "timeInTradeMin": null,
        "mfe": 0.0,
        "mae": 0.0
      }
    }
  ]
}