{
  "generatedAt": "2026-04-16T22:51:20.359623+00:00",
  "symbol": "XAUUSD",
  "interval": "15min",
  "qualityGate": {
    "ok": true,
    "issues": []
  },
  "candles": {
    "count": 1000,
    "from": 1774994400,
    "to": 1776365100
  },
  "summary": {
    "totalOrders": 3,
    "triggeredOrders": 2,
    "slHits": 0,
    "tp1Hits": 1,
    "tpMostHits": 1,
    "winRate": 100.0
  },
  "orders": [
    {
      "source": "TESTER",
      "runId": "RUN-1775058643394-951",
      "orderKey": "TESTER:RUN-1775058643394-951",
      "createdAt": "2026-04-01T15:51:49.489Z",
      "orderType": "BUY_LIMIT",
      "entry": 4755.0,
      "sl": 4734.9,
      "tp1": 4784.39,
      "tpMost": 4784.39,
      "result": {
        "status": "tpmost-hit",
        "triggered": true,
        "triggeredAt": 1775061000,
        "closeReason": "TPMost",
        "closedAt": 1775070000,
        "timeInTradeMin": 150,
        "mfe": 36.8,
        "mae": -3.02
      }
    },
    {
      "source": "EBass",
      "runId": "RUN-1776376042543-372",
      "orderKey": "EBass:RUN-1776376042543-372",
      "createdAt": "2026-04-16T21:48:07.388Z",
      "orderType": "SELL_LIMIT",
      "entry": 4793.85,
      "sl": 4796.29,
      "tp1": 4787.2,
      "tpMost": 4786.08,
      "result": {
        "status": null,
        "triggered": false,
        "triggeredAt": null,
        "closeReason": null,
        "closedAt": null,
        "timeInTradeMin": null,
        "mfe": 0.0,
        "mae": 0.0
      }
    },
    {
      "source": "EKlaETun",
      "runId": "RUN-1776351457978-158",
      "orderKey": "EKlaETun:RUN-1776351457978-158",
      "createdAt": "2026-04-16T14:59:11.372Z",
      "orderType": "SELL_LIMIT",
      "entry": 4795.27,
      "sl": 4801.85,
      "tp1": 4787.15,
      "tpMost": 4785.6,
      "result": {
        "status": "tp1-hit",
        "triggered": true,
        "triggeredAt": 1776353400,
        "closeReason": "TP1",
        "closedAt": 1776357000,
        "timeInTradeMin": 60,
        "mfe": 8.39,
        "mae": -3.33
      }
    }
  ]
}