{
  "generatedAt": "2026-03-30T22:05:02.318029+00:00",
  "symbol": "XAUUSD",
  "interval": "15min",
  "qualityGate": {
    "ok": true,
    "issues": []
  },
  "candles": {
    "count": 1000,
    "from": 1773619200,
    "to": 1774889100
  },
  "summary": {
    "totalOrders": 3,
    "triggeredOrders": 1,
    "slHits": 1,
    "tp1Hits": 0,
    "tpMostHits": 0,
    "winRate": 0.0
  },
  "orders": [
    {
      "source": "TESTER",
      "runId": "RUN-1774903845983-341",
      "orderKey": "TESTER:RUN-1774903845983-341",
      "createdAt": "2026-03-30T20:51:31.419Z",
      "orderType": "SELL_LIMIT",
      "entry": 4512.04,
      "sl": 4521.12,
      "tp1": 4503.49,
      "tpMost": 4503.49,
      "result": {
        "status": null,
        "triggered": false,
        "triggeredAt": null,
        "closeReason": null,
        "closedAt": null,
        "timeInTradeMin": null,
        "mfe": 0.0,
        "mae": 0.0
      }
    },
    {
      "source": "EBass",
      "runId": "RUN-1774885774083-713",
      "orderKey": "EBass:RUN-1774885774083-713",
      "createdAt": "2026-03-30T15:52:53.324Z",
      "orderType": "SELL_LIMIT",
      "entry": 4577.35,
      "sl": 4591.07,
      "tp1": 4541.86,
      "tpMost": 4513.17,
      "result": {
        "status": "pending",
        "triggered": false,
        "triggeredAt": null,
        "closeReason": null,
        "closedAt": null,
        "timeInTradeMin": null,
        "mfe": 0.0,
        "mae": 0.0
      }
    },
    {
      "source": "EKlaETun",
      "runId": "RUN-1774876264776-496",
      "orderKey": "EKlaETun:RUN-1774876264776-496",
      "createdAt": "2026-03-30T13:11:19.576Z",
      "orderType": "BUY_LIMIT",
      "entry": 4558.21,
      "sl": 4545.02,
      "tp1": 4571.4,
      "tpMost": 4582.59,
      "result": {
        "status": "sl-hit",
        "triggered": true,
        "triggeredAt": 1774876500,
        "closeReason": "SL",
        "closedAt": 1774876500,
        "timeInTradeMin": 0,
        "mfe": 0.0,
        "mae": -37.635
      }
    }
  ]
}